snowflake/__init__.py
snowflake/config.py
snowflake/enums.py
snowflake/snowflake.py
snowflake_util-1.0.0b7.dist-info/LICENSE
snowflake_util-1.0.0b7.dist-info/METADATA
snowflake_util-1.0.0b7.dist-info/WHEEL
snowflake_util-1.0.0b7.dist-info/top_level.txt
snowflake_util-1.0.0b7.dist-info/RECORD
