Metadata-Version: 2.1
Name: snowflake-util
Version: 1.0.0b7
Summary: A Python library for generating snowflakes.
Author: TheMultii
Project-URL: Repository, https://github.com/TheMultii/snowflake-util
Keywords: python,snowflake,generator,custom,library,id generator,uid
Classifier: Development Status :: 4 - Beta
Classifier: Intended Audience :: Developers
Classifier: Programming Language :: Python :: 3
Classifier: Programming Language :: Python :: 3.7
Classifier: Programming Language :: Python :: 3.8
Classifier: Programming Language :: Python :: 3.9
Classifier: Programming Language :: Python :: 3.10
Classifier: Programming Language :: Python :: 3.11
Classifier: Programming Language :: Python :: 3.12
Classifier: Programming Language :: Python :: 3.13
Classifier: Operating System :: Unix
Classifier: Operating System :: MacOS :: MacOS X
Classifier: Operating System :: Microsoft :: Windows
License-File: LICENSE
